kittentts/__init__.py
kittentts-0.1.3.dist-info/METADATA
kittentts-0.1.3.dist-info/WHEEL
kittentts-0.1.3.dist-info/RECORD
