Metadata-Version: 2.4
Name: kittentts
Version: 0.1.3
Summary: Implementation of KittenTTS
Author-email: dummyjenil <dummyjenil@gmail.com>
Requires-Dist: espeakng-loader
Requires-Dist: huggingface-hub
Requires-Dist: numpy
Requires-Dist: onnxruntime
Requires-Dist: phonemizer
Requires-Dist: soundfile
